AzuracastPy/__init__.py
AzuracastPy/azuracast_client.py
AzuracastPy/constants.py
AzuracastPy/enums.py
AzuracastPy/exceptions.py
AzuracastPy/request_handler.py
AzuracastPy/models/__init__.py
AzuracastPy/models/helpers.py
AzuracastPy/models/hls_stream.py
AzuracastPy/models/listener.py
AzuracastPy/models/listeners.py
AzuracastPy/models/mount.py
AzuracastPy/models/mount_point.py
AzuracastPy/models/now_playing.py
AzuracastPy/models/playlist.py
AzuracastPy/models/podcast.py
AzuracastPy/models/podcast_episode.py
AzuracastPy/models/queue_item.py
AzuracastPy/models/remote.py
AzuracastPy/models/remote_relay.py
AzuracastPy/models/requestable_song.py
AzuracastPy/models/schedule_item.py
AzuracastPy/models/sftp_user.py
AzuracastPy/models/song.py
AzuracastPy/models/song_history.py
AzuracastPy/models/station.py
AzuracastPy/models/station_file.py
AzuracastPy/models/station_status.py
AzuracastPy/models/streamer.py
AzuracastPy/models/webhook.py
AzuracastPy/models/administration/__init__.py
AzuracastPy/models/administration/admin.py
AzuracastPy/models/administration/admin_station.py
AzuracastPy/models/administration/custom_field.py
AzuracastPy/models/administration/helpers.py
AzuracastPy/models/administration/permissions.py
AzuracastPy/models/administration/relay.py
AzuracastPy/models/administration/role.py
AzuracastPy/models/administration/settings.py
AzuracastPy/models/administration/storage_location.py
AzuracastPy/models/administration/util/admin_resource_operations.py
AzuracastPy/models/util/station_resource_operations.py
AzuracastPy/util/general_util.py
AzuracastPy/util/media_util.py
AzuracastPy-0.0.2.dist-info/LICENSE.md
AzuracastPy-0.0.2.dist-info/METADATA
AzuracastPy-0.0.2.dist-info/WHEEL
AzuracastPy-0.0.2.dist-info/top_level.txt
AzuracastPy-0.0.2.dist-info/RECORD
