Metadata-Version: 2.1
Name: AzuracastPy
Version: 0.0.2
Summary: A Python wrapper for the AzuraCast API
Author-email: Abah Olotuche Gabriel <gabrielabah38@gmail.com>
Project-URL: Homepage, https://github.com/ARandomBoiIsMe/AzuracastPy
Project-URL: Issues, https://github.com/ARandomBoiIsMe/AzuracastPy/issues
Keywords: azuracast,api,wrapper
Classifier: Programming Language :: Python :: 3
Classifier: License :: OSI Approved :: GNU Affero General Public License v3
Classifier: Operating System :: OS Independent
Requires-Python: >=3.8
License-File: LICENSE.md
Requires-Dist: certifi >=2024.2.2
Requires-Dist: charset-normalizer >=3.3.2
Requires-Dist: idna >=3.7
Requires-Dist: lxml >=5.2.1
Requires-Dist: requests >=2.31.0
Requires-Dist: urllib3 >=2.2.1
